{
  "audit": {
    "chain_ok": true,
    "event_count": 1358,
    "events_file": "audit/events.jsonl",
    "events_file_sha256": "e68f63e1774e3ef9ea814add576b0ff77520fed4279e83ae1b80f4c8027750c6",
    "head_hash": "3ae09bd54dc1fa1dc6de17f38d8db79a1a564481566a1a58cec1d085bb40ff8b"
  },
  "files": {
    "daily_report": {
      "path": "reports/daily/2026-07-13.md",
      "sha256": "9e973d6ae7c62ab75e5d7c6189f21650f2b5dfbc628ce2d77d8ec36e849275af"
    },
    "database": {
      "path": "data/portfolio.sqlite",
      "sha256": "17e1dcb0cd39cb72ea5f493882aad886a5aac6b4c95982f3afd1411d8fb03051",
      "tracked_by_git": false
    }
  },
  "generated_at": "2026-07-13T04:37:05Z",
  "manifest_date": "2026-07-13",
  "manifest_version": 1,
  "metrics": {
    "cash": 49219712.44828346,
    "gross_exposure": 45056438.62567496,
    "gross_exposure_pct": 0.9062239761540982,
    "long_market_value": 22777801.710530102,
    "net_exposure_pct": 0.010039743917362962,
    "net_market_value": 499164.79538523866,
    "realized_pnl": 199117.92010302056,
    "return_pct": -0.005622455126625896,
    "short_market_value": 22278636.915144864,
    "total_equity": 49718877.243668705,
    "total_pnl": -281122.7563312948,
    "unrealized_pnl": -480240.67643431533
  },
  "portfolio": {
    "base_currency": "USD",
    "cash": 49219712.44828346,
    "id": 1,
    "initial_cash": 50000000.0,
    "name": "LS Paper Fund",
    "strategy_type": "long_short_hedge_fund"
  },
  "verification": {
    "github_anchor": "git commit history anchors this manifest once pushed",
    "local_command": "python3 -m paper_portfolio audit verify"
  }
}
